easy_spider_tool/__init__.py
easy_spider_tool/data.py
easy_spider_tool/date.py
easy_spider_tool/decorator.py
easy_spider_tool/hash.py
easy_spider_tool/jsons.py
easy_spider_tool/re.py
easy_spider_tool/types.py
easy_spider_tool/verify.py
easy_spider_tool-1.0.17.dist-info/LICENSE
easy_spider_tool-1.0.17.dist-info/METADATA
easy_spider_tool-1.0.17.dist-info/WHEEL
easy_spider_tool-1.0.17.dist-info/top_level.txt
easy_spider_tool-1.0.17.dist-info/RECORD
