Metadata-Version: 2.1
Name: easy-spider-tool
Version: 1.0.17
Summary: 简易、好用的爬虫工具,减少重复代码与文件冗余
Home-page: https://easy-spider-tool.xink.top/
Author: hanxinkong
Author-email: xinkonghan@gmail.com
License: MIT
Keywords: easy,spider,tool
Platform: UNKNOWN
Requires-Python: >=3.6.8
Requires-Dist: dateparser (==1.1.3)
Requires-Dist: jsonpath (==0.82)
Requires-Dist: pytz (==2023.3)
Requires-Dist: setuptools (==41.2.0)
